[
    {
        "x": 717,
        "y": 450,
        "w": 48,
        "h": 96,
        "color": [
            0,
            0,
            255
        ]
    },
    {
        "x": 1297,
        "y": 437,
        "w": 48,
        "h": 96,
        "color": [
            0,
            0,
            255
        ]
    },
    {
        "x": 356,
        "y": 411,
        "w": 48,
        "h": 96,
        "color": [
            0,
            255,
            255
        ]
    },
    {
        "x": 531,
        "y": 400,
        "w": 48,
        "h": 96,
        "color": [
            0,
            255,
            255
        ]
    },
    {
        "x": 1061,
        "y": 395,
        "w": 48,
        "h": 96,
        "color": [
            0,
            255,
            255
        ]
    },
    {
        "x": 1272,
        "y": 374,
        "w": 48,
        "h": 96,
        "color": [
            0,
            0,
            255
        ]
    },
    {
        "x": 263,
        "y": 373,
        "w": 48,
        "h": 96,
        "color": [
            0,
            255,
            255
        ]
    },
    {
        "x": 947,
        "y": 371,
        "w": 48,
        "h": 96,
        "color": [
            0,
            0,
            255
        ]
    },
    {
        "x": 582,
        "y": 369,
        "w": 48,
        "h": 96,
        "color": [
            255,
            255,
            255
        ]
    },
    {
        "x": 654,
        "y": 367,
        "w": 48,
        "h": 96,
        "color": [
            0,
            0,
            255
        ]
    },
    {
        "x": 385,
        "y": 348,
        "w": 48,
        "h": 96,
        "color": [
            0,
            0,
            255
        ]
    },
    {
        "x": 727,
        "y": 334,
        "w": 48,
        "h": 96,
        "color": [
            0,
            0,
            255
        ]
    },
    {
        "x": 1102,
        "y": 332,
        "w": 48,
        "h": 96,
        "color": [
            255,
            255,
            255
        ]
    },
    {
        "x": 1458,
        "y": 327,
        "w": 48,
        "h": 96,
        "color": [
            0,
            0,
            255
        ]
    },
    {
        "x": 455,
        "y": 325,
        "w": 48,
        "h": 96,
        "color": [
            0,
            255,
            255
        ]
    },
    {
        "x": 855,
        "y": 324,
        "w": 48,
        "h": 96,
        "color": [
            0,
            0,
            255
        ]
    },
    {
        "x": 1157,
        "y": 324,
        "w": 48,
        "h": 96,
        "color": [
            0,
            0,
            255
        ]
    },
    {
        "x": 799,
        "y": 323,
        "w": 48,
        "h": 96,
        "color": [
            0,
            0,
            255
        ]
    },
    {
        "x": 1404,
        "y": 320,
        "w": 48,
        "h": 96,
        "color": [
            0,
            255,
            255
        ]
    },
    {
        "x": 491,
        "y": 317,
        "w": 48,
        "h": 96,
        "color": [
            0,
            255,
            255
        ]
    },
    {
        "x": 889,
        "y": 302,
        "w": 48,
        "h": 96,
        "color": [
            0,
            0,
            255
        ]
    },
    {
        "x": 614,
        "y": 287,
        "w": 48,
        "h": 96,
        "color": [
            0,
            0,
            255
        ]
    },
    {
        "x": 1171,
        "y": 252,
        "w": 48,
        "h": 96,
        "color": [
            0,
            0,
            255
        ]
    },
    {
        "x": 778,
        "y": 242,
        "w": 48,
        "h": 96,
        "color": [
            0,
            0,
            255
        ]
    },
    {
        "x": 838,
        "y": 230,
        "w": 48,
        "h": 96,
        "color": [
            0,
            0,
            255
        ]
    }
]